{"stats":{"minecraft:mined":{"minecraft:dark_oak_planks":2,"minecraft:spruce_planks":7,"minecraft:white_bed":1,"minecraft:granite":34,"minecraft:red_sand":18,"minecraft:grass_block":36,"minecraft:spruce_leaves":114,"minecraft:red_mushroom":3,"minecraft:glowstone":27,"minecraft:spruce_sapling":1,"minecraft:iron_ore":44,"minecraft:andesite":5,"minecraft:nether_brick_fence":2,"minecraft:oak_sign":1,"minecraft:stone":117,"minecraft:orange_terracotta":17,"minecraft:dandelion":57,"minecraft:torch":3,"minecraft:poppy":63,"minecraft:chest":1,"minecraft:dead_bush":2,"minecraft:spruce_wall_sign":2,"minecraft:nether_quartz_ore":45,"minecraft:sugar_cane":4,"minecraft:oak_planks":16,"minecraft:diorite":1,"minecraft:wall_torch":4,"minecraft:cactus":2,"minecraft:spruce_log":56,"minecraft:grass":6,"minecraft:oak_log":31,"minecraft:coal_ore":235,"minecraft:sand":124,"minecraft:dirt":135,"minecraft:cobweb":23,"minecraft:terracotta":4,"minecraft:netherrack":29,"minecraft:gold_ore":57,"minecraft:oak_leaves":51},"minecraft:killed":{"minecraft:chicken":2,"minecraft:salmon":1,"minecraft:villager":2,"minecraft:cow":1},"minecraft:picked_up":{"minecraft:wooden_axe":1,"minecraft:iron_chestplate":1,"minecraft:nether_brick_fence":2,"minecraft:chicken":3,"minecraft:string":23,"minecraft:elytra":2,"minecraft:flint_and_steel":1,"minecraft:iron_leggings":1,"minecraft:oak_sign":1,"minecraft:red_sand":10,"minecraft:bucket":8,"minecraft:spruce_planks":9,"minecraft:beef":3,"minecraft:poppy":60,"minecraft:sugar_cane":1,"minecraft:chest":1,"minecraft:egg":2,"minecraft:stick":32,"minecraft:torch":21,"minecraft:golden_axe":1,"minecraft:diorite":4,"minecraft:redstone":16,"minecraft:dark_oak_planks":4,"minecraft:stone_sword":1,"minecraft:cactus":3,"minecraft:stone_shovel":3,"minecraft:shears":1,"minecraft:mutton":1,"minecraft:snowball":13,"minecraft:white_wool":8,"minecraft:cobblestone":131,"minecraft:feather":2,"minecraft:andesite":2,"minecraft:leather":4,"minecraft:red_mushroom":3,"minecraft:oak_log":55,"minecraft:wooden_hoe":1,"minecraft:dirt":200,"minecraft:name_tag":1,"minecraft:orange_terracotta":17,"minecraft:apple":9,"minecraft:stone_pickaxe":1,"minecraft:iron_ore":38,"minecraft:glowstone_dust":73,"minecraft:oak_planks":40,"minecraft:sheep_spawn_egg":5,"minecraft:quartz":43,"minecraft:dandelion":57,"minecraft:sand":113,"minecraft:lava_bucket":10,"minecraft:spruce_sapling":47,"minecraft:white_bed":2,"minecraft:spruce_log":173,"minecraft:gold_ore":50,"minecraft:firework_rocket":26,"minecraft:stone_axe":1,"minecraft:granite":32,"minecraft:painting":4,"minecraft:golden_apple":6,"minecraft:spruce_sign":1,"minecraft:terracotta":5,"minecraft:oak_sapling":11,"minecraft:netherrack":34,"minecraft:coal":202},"minecraft:dropped":{"minecraft:gold_ore":11,"minecraft:iron_ingot":13,"minecraft:sheep_spawn_egg":6,"minecraft:lava_bucket":17,"minecraft:dirt":1,"minecraft:torch":16,"minecraft:sand":2,"minecraft:paper":3,"minecraft:white_wool":1,"minecraft:stone_shovel":1,"minecraft:charcoal":1,"minecraft:spruce_log":46,"minecraft:iron_ore":13,"minecraft:terracotta":1},"minecraft:broken":{"minecraft:stone_pickaxe":2,"minecraft:golden_sword":1,"minecraft:golden_axe":1,"minecraft:stone_axe":3,"minecraft:iron_pickaxe":3,"minecraft:wooden_axe":1,"minecraft:stone_shovel":1},"minecraft:used":{"minecraft:stone_sword":23,"minecraft:flint_and_steel":2,"minecraft:stone_shovel":251,"minecraft:oak_sign":1,"minecraft:spruce_planks":4,"minecraft:torch":50,"minecraft:dirt":182,"minecraft:wooden_axe":40,"minecraft:golden_sword":32,"minecraft:oak_sapling":2,"minecraft:golden_axe":17,"minecraft:stone_pickaxe":262,"minecraft:oak_planks":24,"minecraft:cactus":3,"minecraft:ender_pearl":1,"minecraft:spruce_sign":1,"minecraft:golden_apple":2,"minecraft:white_bed":1,"minecraft:painting":4,"minecraft:wooden_hoe":2,"minecraft:firework_rocket":2,"minecraft:iron_pickaxe":593,"minecraft:spruce_sapling":3,"minecraft:stone_axe":215,"minecraft:bucket":7},"minecraft:crafted":{"minecraft:oak_planks":4,"minecraft:stone_shovel":1,"minecraft:glass":32,"minecraft:stone_pickaxe":1,"minecraft:red_dye":7,"minecraft:orange_dye":14,"minecraft:air":0,"minecraft:paper":3,"minecraft:yellow_dye":19,"minecraft:charcoal":1,"minecraft:stick":4,"minecraft:iron_ingot":3,"minecraft:iron_pickaxe":1,"minecraft:torch":32},"minecraft:killed_by":{"minecraft:player":5,"minecraft:ender_dragon":2},"minecraft:custom":{"minecraft:mob_kills":6,"minecraft:animals_bred":1,"minecraft:interact_with_crafting_table":8,"minecraft:leave_game":10,"minecraft:time_since_death":29846,"minecraft:climb_one_cm":3508,"minecraft:sprint_one_cm":181330,"minecraft:walk_one_cm":671007,"minecraft:drop":117,"minecraft:damage_dealt_absorbed":48,"minecraft:deaths":9,"minecraft:sneak_time":321,"minecraft:walk_under_water_one_cm":19143,"minecraft:jump":2028,"minecraft:walk_on_water_one_cm":26776,"minecraft:interact_with_furnace":12,"minecraft:play_one_minute":253580,"minecraft:sleep_in_bed":5,"minecraft:time_since_rest":13274,"minecraft:damage_taken":5981,"minecraft:damage_absorbed":40,"minecraft:damage_dealt":2321,"minecraft:swim_one_cm":31114,"minecraft:fly_one_cm":1417280,"minecraft:player_kills":3,"minecraft:open_chest":33,"minecraft:crouch_one_cm":161,"minecraft:aviate_one_cm":115308,"minecraft:fall_one_cm":48125}},"DataVersion":2526}